golang_experiments/__init__.py
golang_experiments/exp.py
golang_experiments-0.1.0.dist-info/METADATA
golang_experiments-0.1.0.dist-info/WHEEL
golang_experiments-0.1.0.dist-info/top_level.txt
golang_experiments-0.1.0.dist-info/RECORD
