Metadata-Version: 2.1
Name: golang_experiments
Version: 0.1.0
Summary: A collection of Go programs accessible via Python print calls
Home-page: https://github.com/yourusername/golang_experiments
Author: TVK0305
Author-email: gokultkg01@gmail.com
Requires-Python: >=3.6
